swat_lib/__init__.py
swat_lib-0.1.2.dist-info/LICENSE
swat_lib-0.1.2.dist-info/METADATA
swat_lib-0.1.2.dist-info/WHEEL
swat_lib-0.1.2.dist-info/top_level.txt
swat_lib-0.1.2.dist-info/RECORD
