Metadata-Version: 2.1
Name: swat-lib
Version: 0.1.2
Summary: A small library that includes a test automation runner and utilities
Home-page: https://github.com/user/serato
Author: Benjamin Farrelly
Author-email: benjamin.farrelly@serato.com
License: MIT
Download-URL: https://github.com/serato/swat-lib/archive/v0.1.2.tar.gz
Keywords: Serato,Test,Automation
Platform: UNKNOWN
Classifier: Development Status :: 3 - Alpha
Classifier: Intended Audience :: Developers
Classifier: Topic :: Software Development :: Build Tools
Classifier: License :: OSI Approved :: MIT License
Classifier: Programming Language :: Python :: 3.7
Requires-Python: >=3.6
